LICENSE
django_google_json_style_api/__init__.py
django_google_json_style_api/base.py
django_google_json_style_api/decorators.py
django_google_json_style_api/exceptions.py
django_google_json_style_api/requests.py
django_google_json_style_api/responses.py
django_google_json_style_api-0.3.3.dist-info/LICENSE
django_google_json_style_api-0.3.3.dist-info/WHEEL
django_google_json_style_api-0.3.3.dist-info/METADATA
django_google_json_style_api-0.3.3.dist-info/RECORD
