Metadata-Version: 2.1
Name: django-google-json-style-api
Version: 0.3.3
Summary: Implementation of Google JSON Style Guide for Django
Home-page: https://github.com/azevakin/django-google-json-style-api
License: MIT
Keywords: django,pydantic,json,api
Author: Andrey Zevakin
Requires-Python: >=3.9,<4.0
Classifier: License :: OSI Approved :: MIT License
Classifier: Programming Language :: Python :: 3
Classifier: Programming Language :: Python :: 3.9
Requires-Dist: Django (>=3.2.0,<4.0.0)
Requires-Dist: pydantic (>=1.8.0,<2.0.0)
Project-URL: Repository, https://github.com/azevakin/django-google-json-style-api
